pycodeview/__init__.py
pycodeview/_data/Monoid.ttf
pycodeview/_data/ShareTechMono.ttf
pycodeview/_data/__init__.py
pycodeview/_data/template.html
pycodeview/code_view.py
pycodeview/style.py
pycodeview/syntax_highlighter.py
bb_pycodeview-0.1.3.dist-info/LICENSES.txt
bb_pycodeview-0.1.3.dist-info/METADATA
bb_pycodeview-0.1.3.dist-info/WHEEL
bb_pycodeview-0.1.3.dist-info/entry_points.txt
bb_pycodeview-0.1.3.dist-info/RECORD
