Metadata-Version: 2.1
Name: BB-PyCodeView
Version: 0.1.3
Summary: View highlighted python code
License: MIT
Author: Erik Beebe
Author-email: beebeapps_debugging@tuta.io
Requires-Python: >=3.11,<4.0
Classifier: License :: OSI Approved :: MIT License
Classifier: Programming Language :: Python :: 3
Classifier: Programming Language :: Python :: 3.11
Classifier: Programming Language :: Python :: 3.12
Requires-Dist: bb-apputils (>=0.5.2,<0.6.0)
